MANIFEST.in
README.rst
bootstrap.py
buildout.cfg
setup.py
doc/conf.py
doc/dct_ubm.png
doc/eigenface.png
doc/examples.rst
doc/gabor_graph.png
doc/index.rst
doc/installation.rst
xbob/__init__.py
xbob.example.faceverify.egg-info/PKG-INFO
xbob.example.faceverify.egg-info/SOURCES.txt
xbob.example.faceverify.egg-info/dependency_links.txt
xbob.example.faceverify.egg-info/entry_points.txt
xbob.example.faceverify.egg-info/namespace_packages.txt
xbob.example.faceverify.egg-info/requires.txt
xbob.example.faceverify.egg-info/top_level.txt
xbob.example.faceverify.egg-info/zip-safe
xbob/example/__init__.py
xbob/example/faceverify/__init__.py
xbob/example/faceverify/dct_ubm.py
xbob/example/faceverify/eigenface.py
xbob/example/faceverify/gabor_graph.py
xbob/example/faceverify/utils.py
xbob/example/faceverify/tests/__init__.py
xbob/example/faceverify/tests/dct_feature.hdf5
xbob/example/faceverify/tests/dct_model.hdf5
xbob/example/faceverify/tests/dct_probe.hdf5
xbob/example/faceverify/tests/dct_ubm.hdf5
xbob/example/faceverify/tests/gabor_model.hdf5
xbob/example/faceverify/tests/gabor_probe.hdf5
xbob/example/faceverify/tests/pca_model.hdf5
xbob/example/faceverify/tests/pca_probe.hdf5
xbob/example/faceverify/tests/pca_projector.hdf5