Metadata-Version: 1.1
Name: xbob.example.faceverify
Version: 1.0.0
Summary: Example for using Bob to create face verification systems
Home-page: http://pypi.python.org/pypi/xbob.example.faceverify
Author: Manuel Guenther
Author-email: manuel.guenther@idiap.ch
License: GPLv3
Platform: UNKNOWN
Classifier: Development Status :: 5 - Production/Stable
Classifier: License :: OSI Approved :: GNU General Public License v3 (GPLv3)
Classifier: Intended Audience :: Education
Classifier: Intended Audience :: Science/Research
Classifier: Natural Language :: English
Classifier: Programming Language :: Python
Classifier: Programming Language :: Python :: 3
